src/capo_tools/__init__.py
src/capo_tools/datasets/__init__.py
src/capo_tools/datasets/ETS2/__init__.py
src/capo_tools/datasets/ETS2/dataset.py
src/capo_tools/datasets/ETS2/tools.py
src/capo_tools/datasets/ETS2/ets2_tools/__init__.py
src/capo_tools/datasets/ETS2/ets2_tools/depth_file.py
src/capo_tools/display/__init__.py
src/capo_tools/display/tools/__init__.py
src/capo_tools/display/tools/depth_tools.py
capo_libs-0.0.1a0.dist-info/METADATA
capo_libs-0.0.1a0.dist-info/WHEEL
capo_libs-0.0.1a0.dist-info/top_level.txt
capo_libs-0.0.1a0.dist-info/RECORD
