Metadata-Version: 2.1
Name: capo_libs
Version: 0.0.1a0
Summary: Functions used in CAPO projects
Author: David María Arribas
Requires-Python: >=3.10
